bdacore/__init__.py
bdacore/__main__.py
bdacore/api.py
bdacore/cli.py
bdacore/db/__init__.py
bdacore/db/merge.py
bdacore/metrics/__init__.py
bdacore/metrics/metrics.py
bdacore/neural_networks/__init__.py
bdacore/neural_networks/keras_factory/__init__.py
bdacore/neural_networks/keras_factory/abstract_model_generator.py
bdacore/neural_networks/keras_factory/autoencoders.py
bdacore/neural_networks/keras_factory/text_models.py
bdacore/neural_networks/processing/__init__.py
bdacore/neural_networks/processing/text_classification.py
bdacore/neural_networks/processing/workflow.py
bdacore/outliers/__init__.py
bdacore/outliers/outliers.py
bdacore/outliers/utils.py
bdacore/preprocessing/__init__.py
bdacore/preprocessing/fillna.py
bdacore/preprocessing/shifter.py
bdacore/preprocessing/feature_extraction/__init__.py
bdacore/preprocessing/feature_extraction/categorical.py
bdacore/preprocessing/feature_extraction/distribution.py
bdacore/preprocessing/feature_extraction/text.py
bdacore/preprocessing/feature_extraction/ts.py
bdacore/preprocessing/ts/__init__.py
bdacore/preprocessing/ts/rolling.py
bdacore/text/__init__.py
bdacore/text/lsh.py
bdacore/text/utils.py
bdacore/timeseries/__init__.py
bdacore/timeseries/histrogramdata.py
bdacore/timeseries/seqminer.py
bdacore/utils/__init__.py
bdacore/utils/calibration.py
bdacore/utils/feature_contributions.py
bdacore/utils/prediction_interval.py
bdacore/visualization/__init__.py
bdacore/visualization/metrics.py
bdacore/visualization/prediction_interval_visualization.py
tests/__init__.py
tests/acceptance/__init__.py
tests/acceptance/test_functional_notebooks.py
tests/acceptance/data/hdfs_logs.zip
tests/acceptance/data/kc2.csv
tests/acceptance/data/us-500.csv
tests/acceptance/data/Quora/train.csv.zip
tests/acceptance/data/deft2017/task1-train.csv
tests/acceptance/data/deft2017/task2-train.csv
tests/acceptance/data/rossmann/sample_submission.csv.zip
tests/acceptance/data/rossmann/store.csv.zip
tests/acceptance/data/rossmann/test.csv.zip
bdacore-3.0.1.dist-info/AUTHORS.rst
bdacore-3.0.1.dist-info/LICENSE
bdacore-3.0.1.dist-info/METADATA
bdacore-3.0.1.dist-info/WHEEL
bdacore-3.0.1.dist-info/top_level.txt
bdacore-3.0.1.dist-info/RECORD
