Metadata-Version: 2.1
Name: bdacore
Version: 3.0.1
Summary: DataDriver API package
Home-page: http://datadriver-doc-ddapi.s3-website-eu-west-1.amazonaws.com/
Author: BDA TEAM
Author-email: datadriver@octo.com
License: Apache 2
Platform: UNKNOWN
Classifier: Programming Language :: Python :: 2.7
Classifier: Programming Language :: Python :: 3.6
Requires-Dist: matplotlib (<3.0)
Requires-Dist: pandas (>=0.23.4)
Requires-Dist: scikit-learn (==0.19.*)
Requires-Dist: scikit-learn[alldeps] (==0.19.*)
Requires-Dist: scipy
Requires-Dist: xxhash
Requires-Dist: unidecode
Requires-Dist: gensim
Requires-Dist: future
Requires-Dist: backports.functools-lru-cache
Requires-Dist: importlib ; python_version <= "3.6"
Provides-Extra: test
Requires-Dist: coverage ; extra == 'test'
Requires-Dist: pylint (==1.5.4) ; extra == 'test'
Requires-Dist: pytest ; extra == 'test'
Requires-Dist: pytest-cov ; extra == 'test'
Requires-Dist: nbformat ; extra == 'test'
Requires-Dist: nbconvert ; extra == 'test'
Requires-Dist: pydot ; extra == 'test'
Requires-Dist: graphviz ; extra == 'test'
Requires-Dist: sphinx (>=1.5.*) ; extra == 'test'
Requires-Dist: sphinx-bootstrap-theme (>=0.4.*) ; extra == 'test'
Requires-Dist: nbsphinx (>=0.2.*) ; extra == 'test'
Requires-Dist: sphinx-gallery (>=0.1.*) ; extra == 'test'
Requires-Dist: sphinx-rtd-theme ; extra == 'test'
Requires-Dist: zest.releaser ; extra == 'test'
